LICENSE.md
README.md
setup.py
skywatch/__init__.py
skywatch.egg-info/PKG-INFO
skywatch.egg-info/SOURCES.txt
skywatch.egg-info/dependency_links.txt
skywatch.egg-info/requires.txt
skywatch.egg-info/top_level.txt
skywatch/access/__init__.py
skywatch/access/access.py
skywatch/access/base_constraint.py
skywatch/access/constraints/__init__.py
skywatch/access/constraints/az_el_range.py
skywatch/access/constraints/line_of_sight.py
skywatch/access/constraints/temporal.py
skywatch/attitude/__init__.py
skywatch/attitude/base_attitude.py
skywatch/attitude/builtins/__init__.py
skywatch/attitude/builtins/fixed.py
skywatch/attitude/builtins/lvlh.py
skywatch/attitude/builtins/slerped.py
skywatch/look_angles/__init__.py
skywatch/look_angles/aert.py
skywatch/look_angles/base_look_angle.py
skywatch/look_angles/builtins/__init__.py
skywatch/look_angles/builtins/default_look_strategy.py
skywatch/look_angles/builtins/local_tangent_enu.py
skywatch/skypath/__init__.py
skywatch/skypath/creation.py
skywatch/skypath/skypath.py
skywatch/time/__init__.py
skywatch/time/interval.py
skywatch/utils/__init__.py
skywatch/utils/coverage.py
skywatch/utils/funcs.py
tests/__init__.py
tests/geovista_example.py
tests/test_look_angles.py
tests/test_smoke.py
tests/utils.py