Metadata-Version: 2.1
Name: skywatch
Version: 0.1.3
Summary: Aerospace/astrodynamics analysis library providing high level interfaces for coordinate, attitude, access, and look angle calculations.
Home-page: https://github.com/nsspencer/SkyWatch
Author: Nathan Spencer
License: UNKNOWN
Platform: UNKNOWN
Classifier: Programming Language :: Python :: 3
Classifier: License :: OSI Approved :: MIT License
Classifier: Operating System :: OS Independent
License-File: LICENSE.md
